helloworld.py
jesuslama-0.0.1.dist-info/METADATA
jesuslama-0.0.1.dist-info/WHEEL
jesuslama-0.0.1.dist-info/license.txt
jesuslama-0.0.1.dist-info/top_level.txt
jesuslama-0.0.1.dist-info/RECORD
